pybefit/__init__.py
pybefit/simulate.py
pybefit/agents/__init__.py
pybefit/agents/base.py
pybefit/agents/utils.py
pybefit/agents/jax/__init__.py
pybefit/agents/jax/hsmm_ai.py
pybefit/agents/jax/utils.py
pybefit/agents/torch/__init__.py
pybefit/agents/torch/active_inference.py
pybefit/agents/torch/bayesian.py
pybefit/agents/torch/dynamic_programming.py
pybefit/agents/torch/random.py
pybefit/agents/torch/rl.py
pybefit/inference/__init__.py
pybefit/inference/methods.py
pybefit/inference/models.py
pybefit/inference/posteriors.py
pybefit/inference/priors.py
pybefit/inference/regression.py
pybefit/inference/numpyro/__init__.py
pybefit/inference/numpyro/likelihoods.py
pybefit/inference/numpyro/regression.py
pybefit/inference/pyro/__init__.py
pybefit/inference/pyro/flat.py
pybefit/inference/pyro/hierarchical.py
pybefit/inference/pyro/infer.py
pybefit/inference/pyro/likelihoods.py
pybefit/inference/pyro/mixed.py
pybefit/inference/pyro/nonparametric.py
pybefit/tasks/__init__.py
pybefit/tasks/bandits.py
pybefit/tasks/base.py
pybefit/tasks/rev_learning.py
pybefit/tasks/sat.py
pybefit-0.1.23.dist-info/LICENSE.md
pybefit-0.1.23.dist-info/METADATA
pybefit-0.1.23.dist-info/WHEEL
pybefit-0.1.23.dist-info/top_level.txt
pybefit-0.1.23.dist-info/RECORD
