Metadata-Version: 2.1
Name: pybefit
Version: 0.1.23
Summary: Probabilistic inference for models of behaviour
Home-page: https://github.com/dimarkov/pybefit
Author: Dimitrije Marković
Author-email: dimitrije.markovic@tu-dresden.de
Requires-Python: >=3.10
License-File: LICENSE.md
Requires-Dist: numpyro
Requires-Dist: optax
Requires-Dist: torch
Requires-Dist: pyro-ppl
Requires-Dist: pycm
Requires-Dist: seaborn
Requires-Dist: matplotlib
Requires-Dist: arviz
Requires-Dist: jupyterlab
Requires-Dist: jupyterthemes
Requires-Dist: jupyter-black
